airtest_mobileauto/__init__.py
airtest_mobileauto/control.py
airtest_mobileauto/pick2yaml.py
airtest_mobileauto/tpl_target_pos.png
airtest_mobileauto-2.1.8.4.dist-info/licenses/LICENSE
airtest_mobileauto-2.1.8.4.dist-info/METADATA
airtest_mobileauto-2.1.8.4.dist-info/WHEEL
airtest_mobileauto-2.1.8.4.dist-info/top_level.txt
airtest_mobileauto-2.1.8.4.dist-info/RECORD
