Metadata-Version: 2.4
Name: airtest_mobileauto
Version: 2.1.8.4
Summary: A robust, object-oriented, multi-process mobile app control framework based on AirTest, designed for stable and compatible debugging and automation of devices and apps. Ideal for tasks such as game automation in titles like Honor of Kings, with enhanced stability features including connection checks, automatic retries on failure, and automatic restarts for continuous operation.
Author-email: cndaqiang <who@cndaqiang.ac.cn>
License: MIT
Project-URL: Homepage, https://github.com/cndaqiang/airtest_mobileauto
Classifier: Development Status :: 5 - Production/Stable
Classifier: Intended Audience :: Developers
Classifier: License :: OSI Approved :: MIT License
Classifier: Programming Language :: Python :: 3
Classifier: Topic :: Utilities
Requires-Python: <3.13,>=3.7
License-File: LICENSE
Requires-Dist: airtest
Requires-Dist: pyyaml
Provides-Extra: windows
Requires-Dist: pywin32; extra == "windows"
Dynamic: license-file
